text_embeddings/__init__.py
text_embeddings/base/__init__.py
text_embeddings/byte/__init__.py
text_embeddings/byte/byt5.py
text_embeddings/byte/charformer.py
text_embeddings/hash/__init__.py
text_embeddings/hash/canine.py
text_embeddings/hash/pqrnn.py
text_embeddings/hash/util.py
text_embeddings/pruning/__init__.py
text_embeddings/pruning/ltp.py
text_embeddings/visual/__init__.py
text_embeddings/visual/vtr.py
text_embeddings/x/__init__.py
text_embeddings-0.2.0.dist-info/LICENSE
text_embeddings-0.2.0.dist-info/WHEEL
text_embeddings-0.2.0.dist-info/METADATA
text_embeddings-0.2.0.dist-info/RECORD
